setup.cfg
setup.py
token_cloak/__init__.py
token_cloak/collections.py
token_cloak/exceptions.py
token_cloak/random.py
token_cloak/tokens.py
token_cloak/utils.py
token_cloak.egg-info/PKG-INFO
token_cloak.egg-info/SOURCES.txt
token_cloak.egg-info/dependency_links.txt
token_cloak.egg-info/requires.txt
token_cloak.egg-info/top_level.txt